ecs_connect_cli/__init__.py
ecs_connect_cli/__main__.py
ecs_connect_cli/cli.py
ecs_connect_cli/credentials.py
ecs_connect_cli/helpers.py
ecs_connect_cli/menu.py
ecs_connect_cli/session.py
ecs_connect_cli-1.17.0.dist-info/LICENSE
ecs_connect_cli-1.17.0.dist-info/METADATA
ecs_connect_cli-1.17.0.dist-info/WHEEL
ecs_connect_cli-1.17.0.dist-info/entry_points.txt
ecs_connect_cli-1.17.0.dist-info/RECORD
